pybb_client/__init__.py
pybb_client/bbclient.py
pybb_client-0.0.1.dist-info/METADATA
pybb_client-0.0.1.dist-info/WHEEL
pybb_client-0.0.1.dist-info/licenses/LICENSE
pybb_client-0.0.1.dist-info/RECORD
