Metadata-Version: 2.3
Name: pybb-client
Version: 0.0.1
Summary: Handy Bitbucket client for Python
Project-URL: Homepage, https://github.com/novokrest/automation-tools
Project-URL: Issues, https://github.com/novokrest/automation-tools/issues
Author-email: novokrest <novokrest013@gmail.com>
License-File: LICENSE
Classifier: License :: OSI Approved :: MIT License
Classifier: Operating System :: OS Independent
Classifier: Programming Language :: Python :: 3
Requires-Python: >=3.8
